qBittorrentTools/Scripts.py
qBittorrentTools/Utilities.py
qBittorrentTools/__init__.py
qbittorrent_tools-1.1.1.dist-info/licenses/LICENSE.txt
qbittorrent_tools-1.1.1.dist-info/METADATA
qbittorrent_tools-1.1.1.dist-info/WHEEL
qbittorrent_tools-1.1.1.dist-info/top_level.txt
qbittorrent_tools-1.1.1.dist-info/RECORD
