Metadata-Version: 2.4
Name: qBittorrent-Tools
Version: 1.1.1
Summary: A collection of scripts for managing torrents in qBittorrent
Author-email: Caleb Morrison <cmorrison8191@gmail.com>
Maintainer-email: Caleb Morrison <cmorrison8191@gmail.com>
License: Copyright 2025 Caleb Morrison
Project-URL: Source, https://github.com/cmorrison31/qBittorrent-Tools
Keywords: qBittorrent,Torrent,P2P
Classifier: Development Status :: 5 - Production/Stable
Classifier: Intended Audience :: End Users/Desktop
Classifier: Topic :: Utilities
Classifier: License :: OSI Approved :: MIT License
Classifier: Programming Language :: Python :: 3
Classifier: Programming Language :: Python :: 3.12
Classifier: Programming Language :: Python :: 3.13
Classifier: Programming Language :: Python :: 3 :: Only
Requires-Python: >=3.12
License-File: LICENSE.txt
Requires-Dist: qbittorrent-api
Dynamic: license-file
